[
  {
    "club": "Luleå HF",
    "amount": 10200,
    "currency": "SEK",
    "url": "https://clubs.clubmate.se/luleahockey/",
    "fetched_at": "2025-11-01T09:43:37.572Z",
    "debug": {
      "strategy": "body-max",
      "raw": "10\n200 kr"
    }
  },
  {
    "club": "Brynäs IF",
    "amount": 480,
    "currency": "SEK",
    "url": "https://clubs.clubmate.se/brynas/",
    "fetched_at": "2025-11-01T09:43:40.819Z",
    "debug": {
      "strategy": "hard:.animate-pulse:has-text(\" kr\")",
      "raw": "480 kr"
    }
  },
  {
    "club": "Djurgårdens IF",
    "amount": 4913,
    "currency": "SEK",
    "url": "https://clubs.clubmate.se/difhockey/",
    "fetched_at": "2025-11-01T09:43:43.832Z",
    "debug": {
      "strategy": "pulse",
      "raw": "4 913 kr"
    }
  },
  {
    "club": "Färjestad BK",
    "amount": 600,
    "currency": "SEK",
    "url": "https://clubs.clubmate.se/farjestadbk/",
    "fetched_at": "2025-11-01T09:43:46.699Z",
    "debug": {
      "strategy": "pulse",
      "raw": "600 kr"
    }
  },
  {
    "club": "Frölunda HC",
    "amount": 4330,
    "currency": "SEK",
    "url": "https://clubs.clubmate.se/frolundahockey/",
    "fetched_at": "2025-11-01T09:43:49.544Z",
    "debug": {
      "strategy": "pulse",
      "raw": "4 330 kr"
    }
  },
  {
    "club": "HV 71",
    "amount": 2450,
    "currency": "SEK",
    "url": "https://clubs.clubmate.se/hv71/",
    "fetched_at": "2025-11-01T09:43:52.787Z",
    "debug": {
      "strategy": "pulse",
      "raw": "2 450 kr"
    }
  },
  {
    "club": "Leksands IF",
    "amount": 13470,
    "currency": "SEK",
    "url": "https://clubs.clubmate.se/leksandsif/",
    "fetched_at": "2025-11-01T09:43:55.968Z",
    "debug": {
      "strategy": "pulse",
      "raw": "13 470 kr"
    }
  },
  {
    "club": "Linköping HC",
    "amount": 190,
    "currency": "SEK",
    "url": "https://clubs.clubmate.se/lhc/",
    "fetched_at": "2025-11-01T09:43:59.303Z",
    "debug": {
      "strategy": "pulse",
      "raw": "190 kr"
    }
  },
  {
    "club": "IF Malmö Redhawks",
    "amount": 1170,
    "currency": "SEK",
    "url": "https://clubs.clubmate.se/malmoredhawks/",
    "fetched_at": "2025-11-01T09:44:01.979Z",
    "debug": {
      "strategy": "pulse",
      "raw": "1 170 kr"
    }
  },
  {
    "club": "Örebro HK",
    "amount": 4490,
    "currency": "SEK",
    "url": "https://clubs.clubmate.se/orebrohockey/",
    "fetched_at": "2025-11-01T09:44:05.043Z",
    "debug": {
      "strategy": "pulse",
      "raw": "4 490 kr"
    }
  },
  {
    "club": "Rögle BK",
    "amount": 380,
    "currency": "SEK",
    "url": "https://clubs.clubmate.se/roglebk/",
    "fetched_at": "2025-11-01T09:44:07.656Z",
    "debug": {
      "strategy": "hard:h6.font-bold:has-text(\" kr\")",
      "raw": "380 kr"
    }
  },
  {
    "club": "Skellefteå AIK",
    "amount": 310,
    "currency": "SEK",
    "url": "https://clubs.clubmate.se/skellefteaaik/",
    "fetched_at": "2025-11-01T09:44:10.601Z",
    "debug": {
      "strategy": "pulse",
      "raw": "310 kr"
    }
  },
  {
    "club": "Timrå IK",
    "amount": 9660,
    "currency": "SEK",
    "url": "https://clubs.clubmate.se/timraik/",
    "fetched_at": "2025-11-01T09:44:13.940Z",
    "debug": {
      "strategy": "pulse",
      "raw": "9 660 kr"
    }
  },
  {
    "club": "Växjö Lakers HC",
    "amount": 3980,
    "currency": "SEK",
    "url": "https://clubs.clubmate.se/vaxjolakers/",
    "fetched_at": "2025-11-01T09:44:17.033Z",
    "debug": {
      "strategy": "pulse",
      "raw": "3 980 kr"
    }
  }
]